{
  "chartId": "H135570951596281856",
  "chartType": "5",
  "option": {
    "xAxis": [
      {
        "eventKey": "C-G-109",
        "expanded": true,
        "selected": false,
        "checked": false,
        "loaded": false,
        "loading": false,
        "halfChecked": false,
        "title": "医师",
        "pos": "0-3",
        "dragOver": false,
        "dragOverGapTop": false,
        "dragOverGapBottom": false,
        "dataRef": {
          "id": "C-G-109",
          "customDataColumnId": "C-G-109",
          "key": "physician",
          "title": "医师",
          "displayName": "医师",
          "columnDataType": "STRING",
          "dragGroup": "dimension",
          "customDataSetName": "hospital_data11111爱上大叔大叔",
          "virtualColumnExpress": null,
          "scopedSlots": { "title": "title" }
        },
        "id": "C-G-109",
        "customDataColumnId": "C-G-109",
        "key": "physician",
        "displayName": "医师",
        "columnDataType": "STRING",
        "dragGroup": "dimension",
        "customDataSetName": "hospital_data11111爱上大叔大叔",
        "virtualColumnExpress": null,
        "scopedSlots": { "title": "title" }
      },
      {
        "eventKey": "C-G-110",
        "expanded": true,
        "selected": false,
        "checked": false,
        "loaded": false,
        "loading": false,
        "halfChecked": false,
        "title": "收费细项",
        "pos": "0-4",
        "dragOver": false,
        "dragOverGapTop": false,
        "dragOverGapBottom": false,
        "dataRef": {
          "id": "C-G-110",
          "customDataColumnId": "C-G-110",
          "key": "charge_schedule",
          "title": "收费细项",
          "displayName": "收费细项",
          "columnDataType": "STRING",
          "dragGroup": "dimension",
          "customDataSetName": "hospital_data11111爱上大叔大叔",
          "virtualColumnExpress": null,
          "scopedSlots": { "title": "title" }
        },
        "id": "C-G-110",
        "customDataColumnId": "C-G-110",
        "key": "charge_schedule",
        "displayName": "收费细项",
        "columnDataType": "STRING",
        "dragGroup": "dimension",
        "customDataSetName": "hospital_data11111爱上大叔大叔",
        "virtualColumnExpress": null,
        "scopedSlots": { "title": "title" }
      }
    ],
    "series": [
      {
        "eventKey": "C-G-106",
        "expanded": true,
        "selected": false,
        "checked": false,
        "loaded": false,
        "loading": false,
        "halfChecked": false,
        "title": "医院",
        "pos": "0-0",
        "dragOver": false,
        "dragOverGapTop": false,
        "dragOverGapBottom": false,
        "dataRef": {
          "id": "C-G-106",
          "customDataColumnId": "C-G-106",
          "key": "hospital",
          "title": "医院",
          "displayName": "医院",
          "columnDataType": "STRING",
          "dragGroup": "dimension",
          "customDataSetName": "hospital_data11111爱上大叔大叔",
          "virtualColumnExpress": null,
          "scopedSlots": { "title": "title" }
        },
        "id": "C-G-106",
        "customDataColumnId": "C-G-106",
        "key": "hospital",
        "displayName": "医院",
        "columnDataType": "STRING",
        "dragGroup": "dimension",
        "customDataSetName": "hospital_data11111爱上大叔大叔",
        "virtualColumnExpress": null,
        "scopedSlots": { "title": "title" }
      },
      {
        "eventKey": "C-G-107",
        "expanded": true,
        "selected": false,
        "checked": false,
        "loaded": false,
        "loading": false,
        "halfChecked": false,
        "title": "科室",
        "pos": "0-1",
        "dragOver": false,
        "dragOverGapTop": false,
        "dragOverGapBottom": false,
        "dataRef": {
          "id": "C-G-107",
          "customDataColumnId": "C-G-107",
          "key": "administrative_office",
          "title": "科室",
          "displayName": "科室",
          "columnDataType": "STRING",
          "dragGroup": "dimension",
          "customDataSetName": "hospital_data11111爱上大叔大叔",
          "virtualColumnExpress": null,
          "scopedSlots": { "title": "title" }
        },
        "id": "C-G-107",
        "customDataColumnId": "C-G-107",
        "key": "administrative_office",
        "displayName": "科室",
        "columnDataType": "STRING",
        "dragGroup": "dimension",
        "customDataSetName": "hospital_data11111爱上大叔大叔",
        "virtualColumnExpress": null,
        "scopedSlots": { "title": "title" }
      }
    ],
    "drills": [],
    "color": []
  },
  "rows": [
    { "adaptive_money": 0.8, "owned_money": 4, "physician": "张素琴", "charge_schedule": "静脉注射", "administrative_office": "ZLNK-肿瘤内科", "hospital": "罗湖区人民医院" },
    { "adaptive_money": 4.8, "owned_money": 24, "physician": "张素琴", "charge_schedule": "Ⅰ级护理", "administrative_office": "ZLNK-肿瘤内科", "hospital": "罗湖区人民医院" },
    { "adaptive_money": 0, "owned_money": 0, "physician": "蓝春海", "charge_schedule": "嘱托", "administrative_office": "GK-骨外科", "hospital": "龙岗区人民医院" },
    { "adaptive_money": -0.4, "owned_money": -2, "physician": "彭利霞", "charge_schedule": "静脉输液连续输液第二组起", "administrative_office": "ZLNK-肿瘤内科", "hospital": "福田区人民医院" },
    { "adaptive_money": 0, "owned_money": 0, "physician": "张宁", "charge_schedule": "嘱托", "administrative_office": "HXK-呼吸内科", "hospital": "龙岗区人民医院" },
    { "adaptive_money": 4, "owned_money": 20, "physician": "王岳月", "charge_schedule": "低频脉冲电治疗", "administrative_office": "GK-骨外科", "hospital": "罗湖区人民医院" },
    { "adaptive_money": 1, "owned_money": 5, "physician": "王湛", "charge_schedule": "碱性磷酸酶测定(速率法)", "administrative_office": "XNKMZ-心内科门诊", "hospital": "龙岗区人民医院" }
  ],
  "params": {
    "customDataSetId": "S003",
    "condition": [],
    "dimension": [
      {
        "eventKey": "C-G-115",
        "expanded": true,
        "selected": false,
        "checked": false,
        "loaded": false,
        "loading": false,
        "halfChecked": false,
        "title": "自费金额",
        "pos": "0-0-1",
        "dragOver": false,
        "dragOverGapTop": false,
        "dragOverGapBottom": false,
        "dataRef": {
          "id": "C-G-115",
          "customDataColumnId": "C-G-115",
          "key": "adaptive_money",
          "title": "自费金额",
          "displayName": "自费金额",
          "columnDataType": "INT",
          "dragGroup": "measure",
          "customDataSetName": "hospital_data11111爱上大叔大叔",
          "virtualColumnExpress": null,
          "scopedSlots": { "title": "title" }
        },
        "id": "C-G-115",
        "customDataColumnId": "C-G-115",
        "key": "adaptive_money",
        "displayName": "自费金额",
        "columnDataType": "INT",
        "dragGroup": "measure",
        "customDataSetName": "hospital_data11111爱上大叔大叔",
        "virtualColumnExpress": null,
        "scopedSlots": { "title": "title" },
        "statisType": "SUM",
        "targetColumnId": "C-G-115",
        "aliasName": "adaptive_money",
        "sequence": 0
      },
      {
        "eventKey": "C-G-114",
        "expanded": true,
        "selected": false,
        "checked": false,
        "loaded": false,
        "loading": false,
        "halfChecked": false,
        "title": "金额",
        "pos": "0-0-0",
        "dragOver": false,
        "dragOverGapTop": false,
        "dragOverGapBottom": false,
        "dataRef": {
          "id": "C-G-114",
          "customDataColumnId": "C-G-114",
          "key": "owned_money",
          "title": "金额",
          "displayName": "金额",
          "columnDataType": "INT",
          "dragGroup": "measure",
          "customDataSetName": "hospital_data11111爱上大叔大叔",
          "virtualColumnExpress": null,
          "scopedSlots": { "title": "title" }
        },
        "id": "C-G-114",
        "customDataColumnId": "C-G-114",
        "key": "owned_money",
        "displayName": "金额",
        "columnDataType": "INT",
        "dragGroup": "measure",
        "customDataSetName": "hospital_data11111爱上大叔大叔",
        "virtualColumnExpress": null,
        "scopedSlots": { "title": "title" },
        "statisType": "SUM",
        "targetColumnId": "C-G-114",
        "aliasName": "owned_money",
        "sequence": 0
      },
      {
        "eventKey": "C-G-109",
        "expanded": true,
        "selected": false,
        "checked": false,
        "loaded": false,
        "loading": false,
        "halfChecked": false,
        "title": "医师",
        "pos": "0-3",
        "dragOver": false,
        "dragOverGapTop": false,
        "dragOverGapBottom": false,
        "dataRef": {
          "id": "C-G-109",
          "customDataColumnId": "C-G-109",
          "key": "physician",
          "title": "医师",
          "displayName": "医师",
          "columnDataType": "STRING",
          "dragGroup": "dimension",
          "customDataSetName": "hospital_data11111爱上大叔大叔",
          "virtualColumnExpress": null,
          "scopedSlots": { "title": "title" }
        },
        "id": "C-G-109",
        "customDataColumnId": "C-G-109",
        "key": "physician",
        "displayName": "医师",
        "columnDataType": "STRING",
        "dragGroup": "dimension",
        "customDataSetName": "hospital_data11111爱上大叔大叔",
        "virtualColumnExpress": null,
        "scopedSlots": { "title": "title" },
        "targetColumnId": "C-G-109",
        "aliasName": "physician",
        "sequence": 0,
        "statisType": ""
      },
      {
        "eventKey": "C-G-110",
        "expanded": true,
        "selected": false,
        "checked": false,
        "loaded": false,
        "loading": false,
        "halfChecked": false,
        "title": "收费细项",
        "pos": "0-4",
        "dragOver": false,
        "dragOverGapTop": false,
        "dragOverGapBottom": false,
        "dataRef": {
          "id": "C-G-110",
          "customDataColumnId": "C-G-110",
          "key": "charge_schedule",
          "title": "收费细项",
          "displayName": "收费细项",
          "columnDataType": "STRING",
          "dragGroup": "dimension",
          "customDataSetName": "hospital_data11111爱上大叔大叔",
          "virtualColumnExpress": null,
          "scopedSlots": { "title": "title" }
        },
        "id": "C-G-110",
        "customDataColumnId": "C-G-110",
        "key": "charge_schedule",
        "displayName": "收费细项",
        "columnDataType": "STRING",
        "dragGroup": "dimension",
        "customDataSetName": "hospital_data11111爱上大叔大叔",
        "virtualColumnExpress": null,
        "scopedSlots": { "title": "title" },
        "targetColumnId": "C-G-110",
        "aliasName": "charge_schedule",
        "sequence": 0,
        "statisType": ""
      }
    ],
    "metric": [
      {
        "eventKey": "C-G-106",
        "expanded": true,
        "selected": false,
        "checked": false,
        "loaded": false,
        "loading": false,
        "halfChecked": false,
        "title": "医院",
        "pos": "0-0",
        "dragOver": false,
        "dragOverGapTop": false,
        "dragOverGapBottom": false,
        "dataRef": {
          "id": "C-G-106",
          "customDataColumnId": "C-G-106",
          "key": "hospital",
          "title": "医院",
          "displayName": "医院",
          "columnDataType": "STRING",
          "dragGroup": "dimension",
          "customDataSetName": "hospital_data11111爱上大叔大叔",
          "virtualColumnExpress": null,
          "scopedSlots": { "title": "title" }
        },
        "id": "C-G-106",
        "customDataColumnId": "C-G-106",
        "key": "hospital",
        "displayName": "医院",
        "columnDataType": "STRING",
        "dragGroup": "dimension",
        "customDataSetName": "hospital_data11111爱上大叔大叔",
        "virtualColumnExpress": null,
        "scopedSlots": { "title": "title" },
        "aliasName": "hospital",
        "targetColumnId": "C-G-106",
        "sequence": 0,
        "statisType": ""
      },
      {
        "eventKey": "C-G-107",
        "expanded": true,
        "selected": false,
        "checked": false,
        "loaded": false,
        "loading": false,
        "halfChecked": false,
        "title": "科室",
        "pos": "0-1",
        "dragOver": false,
        "dragOverGapTop": false,
        "dragOverGapBottom": false,
        "dataRef": {
          "id": "C-G-107",
          "customDataColumnId": "C-G-107",
          "key": "administrative_office",
          "title": "科室",
          "displayName": "科室",
          "columnDataType": "STRING",
          "dragGroup": "dimension",
          "customDataSetName": "hospital_data11111爱上大叔大叔",
          "virtualColumnExpress": null,
          "scopedSlots": { "title": "title" }
        },
        "id": "C-G-107",
        "customDataColumnId": "C-G-107",
        "key": "administrative_office",
        "displayName": "科室",
        "columnDataType": "STRING",
        "dragGroup": "dimension",
        "customDataSetName": "hospital_data11111爱上大叔大叔",
        "virtualColumnExpress": null,
        "scopedSlots": { "title": "title" },
        "aliasName": "administrative_office",
        "targetColumnId": "C-G-107",
        "sequence": 0,
        "statisType": ""
      }
    ]
  }
}
